{"id": "sys", "path": "C:\\Anaconda3\\Lib\\mypy\\typeshed\\stdlib\\3\\sys.pyi", "mtime": 1516708837, "size": 5029, "hash": "2d2682ee49824db741ccb01ac125aad4", "data_mtime": 1524761359, "dependencies": ["typing", "types", "mypy_extensions", "builtins"], "suppressed": [], "child_modules": [], "options": {"disallow_any_decorated": false, "ignore_missing_imports": true, "disallow_any_explicit": false, "disallow_any_unimported": false, "strict_optional_whitelist": null, "show_none_errors": true, "platform": "win32", "disallow_any_generics": false, "disallow_untyped_defs": false, "disallow_untyped_decorators": false, "check_untyped_defs": false, "strict_boolean": false, "warn_return_any": false, "disallow_subclassing_any": false, "disallow_untyped_calls": false, "no_implicit_optional": false, "strict_optional": false, "ignore_errors": false, "follow_imports": "silent", "quick_and_dirty": false, "disallow_any_expr": false, "warn_no_return": true}, "dep_prios": [5, 5, 5, 5], "interface_hash": "e433ed772f99757352c2a10fe342e649", "version_id": "0.560", "ignore_all": false}
